{"stats":{"minecraft:custom":{"minecraft:time_since_rest":7938,"minecraft:walk_one_cm":3160,"minecraft:leave_game":13,"minecraft:damage_taken":993,"minecraft:play_time":58997,"minecraft:jump":88,"minecraft:time_since_death":7889,"minecraft:sprint_one_cm":10535,"minecraft:fall_one_cm":3677,"minecraft:total_world_time":58997,"minecraft:fly_one_cm":177920,"minecraft:sneak_time":52,"minecraft:deaths":11},"minecraft:used":{"minecraft:grass_block":26},"minecraft:killed_by":{"minecraft:creeper":2}},"DataVersion":4440}